SingleOrigin/Element_table.txt
SingleOrigin/__init__.py
SingleOrigin/eds.py
SingleOrigin/measure_lattice.py
singleorigin-3.0.0.dist-info/licenses/LICENSE.txt
singleorigin-3.0.0.dist-info/METADATA
singleorigin-3.0.0.dist-info/WHEEL
singleorigin-3.0.0.dist-info/top_level.txt
singleorigin-3.0.0.dist-info/RECORD
