Metadata-Version: 2.4
Name: SingleOrigin
Version: 3.0.0
Summary: Crystallographic analysis for STEM data
Author-email: Stephen Funni <sdf68@cornell.edu>
Project-URL: homepage, https://github.com/sdfunni/SingleOrigin
Classifier: Programming Language :: Python :: 3
Classifier: License :: OSI Approved :: GNU General Public License v3 or later (GPLv3+)
Classifier: Operating System :: OS Independent
Requires-Python: >=3.9
License-File: LICENSE.txt
Requires-Dist: psutil
Requires-Dist: joblib
Requires-Dist: tqdm
Requires-Dist: PyQt5
Requires-Dist: numpy>=1.24.1
Requires-Dist: pandas
Requires-Dist: scipy>=1.9.0
Requires-Dist: matplotlib
Requires-Dist: matplotlib_scalebar
Requires-Dist: imageio
Requires-Dist: scikit-image
Requires-Dist: scikit-learn
Requires-Dist: tifffile
Requires-Dist: ase
Requires-Dist: ncempy
Requires-Dist: hyperspy>=1.7.5
Requires-Dist: exspy
Requires-Dist: h5py
Requires-Dist: cmocean
Requires-Dist: sphinx_rtd_theme
Dynamic: license-file
